tvDatafeed/__init__.py
tvDatafeed/main.py
tvdatafeed-2.1.0.dist-info/LICENSE
tvdatafeed-2.1.0.dist-info/METADATA
tvdatafeed-2.1.0.dist-info/WHEEL
tvdatafeed-2.1.0.dist-info/top_level.txt
tvdatafeed-2.1.0.dist-info/RECORD
