Metadata-Version: 2.1
Name: tvdatafeed
Version: 2.1.0
Summary: TradingView historical data downloader
Home-page: https://github.com/StreamAlpha/tvdatafeed/
Author: @StreamAlpha
Author-email: 
License: MIT License
Project-URL: YouTube, https://youtube.com/StreamAlpha?sub_confirmation=1
Project-URL: Funding, https://www.buymeacoffee.com/StreamAlpha
Project-URL: Telegram Channel, https://t.me/streamAlpha
Project-URL: Source, https://github.com/StreamAlpha/tvdatafeed/
Project-URL: Tracker, https://github.com/StreamAlpha/tvdatafeed/issues
Platform: UNKNOWN
License-File: LICENSE
Requires-Dist: setuptools
Requires-Dist: pandas
Requires-Dist: websocket-client
Requires-Dist: requests
